mlcvzoo_base/__init__.py
mlcvzoo_base/py.typed
mlcvzoo_base/api/__init__.py
mlcvzoo_base/api/configuration.py
mlcvzoo_base/api/exceptions.py
mlcvzoo_base/api/interfaces.py
mlcvzoo_base/api/model.py
mlcvzoo_base/api/registry.py
mlcvzoo_base/api/structs.py
mlcvzoo_base/api/data/__init__.py
mlcvzoo_base/api/data/annotation.py
mlcvzoo_base/api/data/annotation_attributes.py
mlcvzoo_base/api/data/annotation_builder.py
mlcvzoo_base/api/data/annotation_class_mapper.py
mlcvzoo_base/api/data/annotation_parser.py
mlcvzoo_base/api/data/annotation_writer.py
mlcvzoo_base/api/data/bounding_box.py
mlcvzoo_base/api/data/box.py
mlcvzoo_base/api/data/class_identifier.py
mlcvzoo_base/api/data/classification.py
mlcvzoo_base/api/data/dataset_info.py
mlcvzoo_base/api/data/geometric_classifiction.py
mlcvzoo_base/api/data/metrics.py
mlcvzoo_base/api/data/ocr_perception.py
mlcvzoo_base/api/data/segmentation.py
mlcvzoo_base/api/data/types.py
mlcvzoo_base/configuration/__init__.py
mlcvzoo_base/configuration/annotation_handler_config.py
mlcvzoo_base/configuration/class_mapping_config.py
mlcvzoo_base/configuration/config_registry.py
mlcvzoo_base/configuration/device_query.py
mlcvzoo_base/configuration/mlfow_config.py
mlcvzoo_base/configuration/model_config.py
mlcvzoo_base/configuration/reduction_mapping_config.py
mlcvzoo_base/configuration/replacement_config.py
mlcvzoo_base/configuration/structs.py
mlcvzoo_base/configuration/utils.py
mlcvzoo_base/configuration/visualization_config.py
mlcvzoo_base/data_preparation/__init__.py
mlcvzoo_base/data_preparation/annotation_handler.py
mlcvzoo_base/data_preparation/structs.py
mlcvzoo_base/data_preparation/utils.py
mlcvzoo_base/data_preparation/annotation_builder/__init__.py
mlcvzoo_base/data_preparation/annotation_builder/coco_annotation_builder.py
mlcvzoo_base/data_preparation/annotation_builder/csv_annotation_builder.py
mlcvzoo_base/data_preparation/annotation_builder/cvat_annotation_builder.py
mlcvzoo_base-6.2.1.dist-info/LICENSE
mlcvzoo_base-6.2.1.dist-info/METADATA
mlcvzoo_base-6.2.1.dist-info/WHEEL
mlcvzoo_base-6.2.1.dist-info/top_level.txt
mlcvzoo_base-6.2.1.dist-info/RECORD
